README.md
setup.py
day/__init__.py
day.egg-info/PKG-INFO
day.egg-info/SOURCES.txt
day.egg-info/dependency_links.txt
day.egg-info/top_level.txt